snappysonic/__init__.py
snappysonic/__main__.py
snappysonic/_version.py
snappysonic/algorithms/__init__.py
snappysonic/algorithms/algorithms.py
snappysonic/overlay_widget/__init__.py
snappysonic/overlay_widget/overlay.py
snappysonic/ui/__init__.py
snappysonic/ui/snappysonic_command_line.py
snappysonic/ui/snappysonic_demo.py
snappysonic-0.0.8.dist-info/LICENSE
snappysonic-0.0.8.dist-info/METADATA
snappysonic-0.0.8.dist-info/WHEEL
snappysonic-0.0.8.dist-info/entry_points.txt
snappysonic-0.0.8.dist-info/top_level.txt
snappysonic-0.0.8.dist-info/RECORD
