Metadata-Version: 2.1
Name: snappysonic
Version: 0.0.8
Summary: snappysonic provides an application to simulate an ultrasound probe moving over a body torso, it is intended for public engagement events"
Home-page: https://github.com/SciKit-Surgery/snappysonic
Author: Stephen Thompson
Author-email: s.thompson@ucl.ac.uk
License: BSD-3 license
Keywords: medical imaging education
Platform: UNKNOWN
Classifier: Development Status :: 3 - Alpha
Classifier: Intended Audience :: Developers
Classifier: Intended Audience :: Healthcare Industry
Classifier: Intended Audience :: Information Technology
Classifier: Intended Audience :: Science/Research
Classifier: License :: OSI Approved :: BSD License
Classifier: Programming Language :: Python
Classifier: Programming Language :: Python :: 3
Classifier: Topic :: Scientific/Engineering :: Information Analysis
Classifier: Topic :: Scientific/Engineering :: Medical Science Apps.
License-File: LICENSE
Requires-Dist: opencv-contrib-python
Requires-Dist: scikit-surgeryimage (>=0.6.0)
Requires-Dist: scikit-surgeryutils (>=1.2.1)
Requires-Dist: scikit-surgerynditracker
Requires-Dist: scikit-surgeryarucotracker
Requires-Dist: numpy
Requires-Dist: PySide2
